signalyzer/__init__.py
signalyzer/constants.py
signalyzer/statemachine/__init__.py
signalyzer/trace/__init__.py
signalyzer-0.3.0.dist-info/LICENSE
signalyzer-0.3.0.dist-info/METADATA
signalyzer-0.3.0.dist-info/WHEEL
signalyzer-0.3.0.dist-info/top_level.txt
signalyzer-0.3.0.dist-info/RECORD
