Metadata-Version: 2.1
Name: signalyzer
Version: 0.3.0
Summary: Signal analyzer for time-discrete, equidistant measured signals
Home-page: https://gitlab.com/signalytics/signalyzer/
Download-URL: https://gitlab.com/signalytics/signalyzer/-/packages
Author: Jochen Gerhaeusser
Author-email: jochen_privat@gmx.de
License: BSD-3-Clause
Project-URL: Issue Tracker, https://gitlab.com/signalytics/signalyzer/-/issues/
Project-URL: Documentation, https://signalyzer.readthedocs.io
Project-URL: Source Code, https://gitlab.com/signalytics/signalyzer/
Keywords: time-discrete signals,equidistant signals,signal processing,signal analysis,statistics,visualisation
Platform: any
Classifier: Development Status :: 5 - Production/Stable
Classifier: Environment :: Web Environment
Classifier: Intended Audience :: Developers
Classifier: Intended Audience :: Education
Classifier: Intended Audience :: Science/Research
Classifier: License :: OSI Approved :: BSD License
Classifier: Natural Language :: English
Classifier: Operating System :: OS Independent
Classifier: Programming Language :: Python
Classifier: Programming Language :: Python :: 3.10
Classifier: Programming Language :: Python :: 3.11
Classifier: Topic :: Education
Classifier: Topic :: Scientific/Engineering
Classifier: Topic :: Scientific/Engineering :: Information Analysis
Classifier: Topic :: Scientific/Engineering :: Visualization
Requires-Python: >=3.10
License-File: LICENSE
Requires-Dist: numpy (>=1.24.1)
Requires-Dist: scipy (>=1.10.1)
Requires-Dist: pandas (>=2.0.0)
Requires-Dist: plotly (>=5.14.1)
